simpl_client/__init__.py
simpl_client/asyn/__init__.py
simpl_client/asyn/games_client.py
simpl_client/syn/__init__.py
simpl_client/syn/games_client.py
tests/__init__.py
tests/conftest.py
tests/test_async_games_client.py
tests/test_sync_games_client.py
simpl_client-0.8.1.dist-info/LICENSE
simpl_client-0.8.1.dist-info/METADATA
simpl_client-0.8.1.dist-info/WHEEL
simpl_client-0.8.1.dist-info/top_level.txt
simpl_client-0.8.1.dist-info/RECORD
