Metadata-Version: 2.1
Name: simpl-client
Version: 0.8.1
Summary: Python clients for accessing simpl-games-api
Home-page: https://github.com/simplworld/simpl-client
Author: 
Author-email: 
License: UNKNOWN
Platform: UNKNOWN
Classifier: Development Status :: 4 - Beta
Classifier: Environment :: Web Environment
Classifier: Intended Audience :: Developers
Classifier: License :: OSI Approved :: GNU General Public License v2 (GPLv2)
Classifier: Operating System :: OS Independent
Classifier: Programming Language :: Python :: 3
Classifier: Framework :: Django
Requires-Dist: genericclient-aiohttp (<1.5,>=1.4.2)
Requires-Dist: genericclient (<1.5,>=1.4.2)
